gitSOC/__init__.py
gitSOC/managedRepo.py
gitSOC/cmd/__init__.py
gitSOC/cmd/cmd.py
gitSOC/cmd/config.py
gitSOC/cmd/disable.py
gitSOC/cmd/enable.py
gitSOC/cmd/fetch.py
gitSOC/cmd/fix.py
gitSOC/cmd/info.py
gitSOC/cmd/interactive.py
gitSOC/cmd/linkup.py
gitSOC/cmd/pull.py
gitSOC/cmd/push.py
gitSOC/cmd/pushpull.py
gitSOC/cmd/register.py
gitSOC/cmd/status.py
gitSOC/tools/main.py
git_soc-0.1.dist-info/METADATA
git_soc-0.1.dist-info/WHEEL
git_soc-0.1.dist-info/entry_points.txt
git_soc-0.1.dist-info/licenses/LICENSE
git_soc-0.1.dist-info/RECORD
