Metadata-Version: 2.3
Name: git-soc
Version: 0.1
Summary: A multi-repo manager for git
Project-URL: Homepage, https://github.com/hardaker/git-soc
Author-email: Wes Hardaker <opensource@hardakers.net>
License-File: LICENSE
Classifier: Operating System :: OS Independent
Classifier: Programming Language :: Python :: 3
Requires-Python: >=3.7
Requires-Dist: gitpython
Requires-Dist: pyaml
Requires-Dist: rich
